vcfempy/__init__.py
vcfempy/flow.py
vcfempy/materials.py
vcfempy/meshgen.py
vcfempy-0.0.14.dist-info/LICENSE
vcfempy-0.0.14.dist-info/METADATA
vcfempy-0.0.14.dist-info/WHEEL
vcfempy-0.0.14.dist-info/top_level.txt
vcfempy-0.0.14.dist-info/RECORD
