Metadata-Version: 2.1
Name: vcfempy
Version: 0.0.14
Summary: A Python package for the Voronoi Cell Finite Element Method
Home-page: https://github.com/karcheba1/vcfempy
Author: Brandon Karchewski
Author-email: brandon.karchewski@ucalgary.ca
License: UNKNOWN
Project-URL: GitHub Repo, https://github.com/karcheba1/vcfempy
Project-URL: Bug Tracker, https://github.com/karcheba1/vcfempy/issues/
Project-URL: Documentation, https://vcfempy.readthedocs.io/en/latest/
Platform: UNKNOWN
Classifier: Programming Language :: Python :: 3
Classifier: License :: OSI Approved :: MIT License
Classifier: Operating System :: OS Independent
Requires-Python: >=3.8
License-File: LICENSE
Requires-Dist: numpy (>=1.22.0)
Requires-Dist: scipy (>=1.8.0)
Requires-Dist: matplotlib (>=3.4.0)
Requires-Dist: shapely (>=1.8.0)
